fizgrid/__init__.py
fizgrid/entities.py
fizgrid/grid.py
fizgrid/queue.py
fizgrid/utils.py
fizgrid/helpers/__init__.py
fizgrid/helpers/waypoint_timing/__init__.py
fizgrid/helpers/waypoint_timing/acceleration.py
fizgrid/helpers/waypoint_timing/simple.py
fizgrid/helpers/waypoint_timing/utils.py
fizgrid-1.10.0.dist-info/licenses/LICENSE
fizgrid-1.10.0.dist-info/METADATA
fizgrid-1.10.0.dist-info/WHEEL
fizgrid-1.10.0.dist-info/top_level.txt
fizgrid-1.10.0.dist-info/RECORD
