Metadata-Version: 2.4
Name: fizgrid
Version: 1.10.0
Summary: Simulate grid based environments.
Author: Connor Makowski
Author-email: Connor Makowski <conmak@mit.edu>
Project-URL: Homepage, https://github.com/connor-makowski/fizgrid
Project-URL: Bug Tracker, https://github.com/connor-makowski/fizgrid/issues
Project-URL: Documentation, https://connor-makowski.github.io/fizgrid/index.html
Classifier: Programming Language :: Python :: 3
Classifier: License :: OSI Approved :: MIT License
Classifier: Operating System :: OS Independent
Requires-Python: >=3.11
License-File: LICENSE
Requires-Dist: type_enforced<3.0.0,>=2.2.2
Dynamic: license-file
